LICENSE
pychatz/.DS_Store
pychatz/__init__.py
pychatz/main.py
pychatz-1.0.1.dist-info/entry_points.txt
pychatz-1.0.1.dist-info/LICENSE
pychatz-1.0.1.dist-info/WHEEL
pychatz-1.0.1.dist-info/METADATA
pychatz-1.0.1.dist-info/RECORD
